t2t/__init__.py
t2t/arguments.py
t2t/t2t.py
t2t/utils.py
t2t_tuner-0.1.4.dist-info/LICENSE
t2t_tuner-0.1.4.dist-info/METADATA
t2t_tuner-0.1.4.dist-info/WHEEL
t2t_tuner-0.1.4.dist-info/top_level.txt
t2t_tuner-0.1.4.dist-info/RECORD
