Metadata-Version: 2.1
Name: t2t-tuner
Version: 0.1.4
Summary: Convenient Text-to-Text Training for Transformers
Home-page: https://github.com/tlkh/t2t-tuner
Author: Timothy Liu
Author-email: tlkh.xms@gmail.com
License: UNKNOWN
Project-URL: Bug Tracker, https://github.com/tlkh/t2t-tuner/issues
Platform: UNKNOWN
Classifier: Programming Language :: Python :: 3
Requires-Python: >=3.6
License-File: LICENSE
Requires-Dist: tqdm
Requires-Dist: ipywidgets
Requires-Dist: datasets
Requires-Dist: sentencepiece
Requires-Dist: sacrebleu (>=1.5)
Requires-Dist: transformers
Requires-Dist: pandas
Requires-Dist: deepspeed
